{
  ".schema_version": "1",
  "name": "archive",
  "type": "provider",
  "version": "v1.2.1",
  "provider": {},
  "resources": {
    "archive_file": {
      "excludes": {
        "Type": "Set",
        "Optional": true,
        "ConflictsWith": [
          "source_content",
          "source_content_filename",
          "source_file"
        ],
        "Elem": {
          "Type": "SchemaElements",
          "ElementsType": "String"
        }
      },
      "output_base64sha256": {
        "Type": "String",
        "Description": "Base64 Encoded SHA256 checksum of output file",
        "Computed": true
      },
      "output_md5": {
        "Type": "String",
        "Description": "MD5 of output file",
        "Computed": true
      },
      "output_path": {
        "Type": "String",
        "Required": true
      },
      "output_sha": {
        "Type": "String",
        "Description": "SHA1 checksum of output file",
        "Computed": true
      },
      "output_size": {
        "Type": "Int",
        "Computed": true
      },
      "source": {
        "Type": "Set",
        "Optional": true,
        "Computed": true,
        "ConflictsWith": [
          "source_file",
          "source_dir",
          "source_content",
          "source_content_filename"
        ],
        "Elem": {
          "Type": "SchemaInfo",
          "Info": {
            "content": {
              "Type": "String",
              "Required": true
            },
            "filename": {
              "Type": "String",
              "Required": true
            }
          }
        }
      },
      "source_content": {
        "Type": "String",
        "Optional": true,
        "ConflictsWith": [
          "source_file",
          "source_dir"
        ]
      },
      "source_content_filename": {
        "Type": "String",
        "Optional": true,
        "ConflictsWith": [
          "source_file",
          "source_dir"
        ]
      },
      "source_dir": {
        "Type": "String",
        "Optional": true,
        "ConflictsWith": [
          "source_content",
          "source_content_filename",
          "source_file"
        ]
      },
      "source_file": {
        "Type": "String",
        "Optional": true,
        "ConflictsWith": [
          "source_content",
          "source_content_filename",
          "source_dir"
        ]
      },
      "type": {
        "Type": "String",
        "Required": true
      }
    }
  },
  "data-sources": {
    "archive_file": {
      "excludes": {
        "Type": "Set",
        "Optional": true,
        "ConflictsWith": [
          "source_content",
          "source_content_filename",
          "source_file"
        ],
        "Elem": {
          "Type": "SchemaElements",
          "ElementsType": "String"
        }
      },
      "output_base64sha256": {
        "Type": "String",
        "Description": "Base64 Encoded SHA256 checksum of output file",
        "Computed": true
      },
      "output_md5": {
        "Type": "String",
        "Description": "MD5 of output file",
        "Computed": true
      },
      "output_path": {
        "Type": "String",
        "Required": true
      },
      "output_sha": {
        "Type": "String",
        "Description": "SHA1 checksum of output file",
        "Computed": true
      },
      "output_size": {
        "Type": "Int",
        "Computed": true
      },
      "source": {
        "Type": "Set",
        "Optional": true,
        "Computed": true,
        "ConflictsWith": [
          "source_file",
          "source_dir",
          "source_content",
          "source_content_filename"
        ],
        "Elem": {
          "Type": "SchemaInfo",
          "Info": {
            "content": {
              "Type": "String",
              "Required": true
            },
            "filename": {
              "Type": "String",
              "Required": true
            }
          }
        }
      },
      "source_content": {
        "Type": "String",
        "Optional": true,
        "ConflictsWith": [
          "source_file",
          "source_dir"
        ]
      },
      "source_content_filename": {
        "Type": "String",
        "Optional": true,
        "ConflictsWith": [
          "source_file",
          "source_dir"
        ]
      },
      "source_dir": {
        "Type": "String",
        "Optional": true,
        "ConflictsWith": [
          "source_content",
          "source_content_filename",
          "source_file"
        ]
      },
      "source_file": {
        "Type": "String",
        "Optional": true,
        "ConflictsWith": [
          "source_content",
          "source_content_filename",
          "source_dir"
        ]
      },
      "type": {
        "Type": "String",
        "Required": true
      }
    }
  }
}