{
  ".schema_version": "1",
  "name": "profitbricks",
  "type": "provider",
  "version": "v1.4.4",
  "provider": {
    "endpoint": {
      "Type": "String",
      "Optional": true,
      "Description": "ProfitBricks REST API URL.",
      "DefaultFunc": "ENV(PROFITBRICKS_API_URL)"
    },
    "password": {
      "Type": "String",
      "Optional": true,
      "Description": "ProfitBricks password for API operations. If token is provided, token is preferred",
      "DefaultFunc": "ENV(PROFITBRICKS_PASSWORD)",
      "ConflictsWith": [
        "token"
      ]
    },
    "retries": {
      "Type": "Int",
      "Optional": true,
      "Deprecated": "Timeout is used instead of this functionality",
      "Default": {
        "Type": "int",
        "Value": "50"
      }
    },
    "token": {
      "Type": "String",
      "Optional": true,
      "Description": "Profitbricks bearer token for API operations.",
      "DefaultFunc": "ENV(PROFITBRICKS_TOKEN)",
      "ConflictsWith": [
        "username",
        "password"
      ]
    },
    "username": {
      "Type": "String",
      "Optional": true,
      "Description": "ProfitBricks username for API operations. If token is provided, token is preferred",
      "DefaultFunc": "ENV(PROFITBRICKS_USERNAME)",
      "ConflictsWith": [
        "token"
      ]
    }
  },
  "resources": {
    "profitbricks_datacenter": {
      "__timeouts__": [
        "create",
        "update",
        "delete",
        "default"
      ],
      "description": {
        "Type": "String",
        "Optional": true,
        "Computed": true
      },
      "location": {
        "Type": "String",
        "Required": true
      },
      "name": {
        "Type": "String",
        "Required": true
      }
    },
    "profitbricks_firewall": {
      "__timeouts__": [
        "create",
        "update",
        "delete",
        "default"
      ],
      "datacenter_id": {
        "Type": "String",
        "Required": true
      },
      "icmp_code": {
        "Type": "String",
        "Optional": true
      },
      "icmp_type": {
        "Type": "String",
        "Optional": true
      },
      "name": {
        "Type": "String",
        "Optional": true
      },
      "nic_id": {
        "Type": "String",
        "Required": true
      },
      "port_range_end": {
        "Type": "Int",
        "Optional": true
      },
      "port_range_start": {
        "Type": "Int",
        "Optional": true
      },
      "protocol": {
        "Type": "String",
        "Required": true
      },
      "server_id": {
        "Type": "String",
        "Required": true
      },
      "source_ip": {
        "Type": "String",
        "Optional": true
      },
      "source_mac": {
        "Type": "String",
        "Optional": true
      },
      "target_ip": {
        "Type": "String",
        "Optional": true
      }
    },
    "profitbricks_group": {
      "__timeouts__": [
        "create",
        "update",
        "delete",
        "default"
      ],
      "access_activity_log": {
        "Type": "Bool",
        "Optional": true
      },
      "create_datacenter": {
        "Type": "Bool",
        "Optional": true
      },
      "create_snapshot": {
        "Type": "Bool",
        "Optional": true
      },
      "name": {
        "Type": "String",
        "Required": true
      },
      "reserve_ip": {
        "Type": "Bool",
        "Optional": true
      },
      "user_id": {
        "Type": "String",
        "Optional": true
      },
      "users": {
        "Type": "Set",
        "Computed": true,
        "Elem": {
          "Type": "SchemaInfo",
          "Info": {
            "administrator": {
              "Type": "Bool",
              "Computed": true
            },
            "email": {
              "Type": "String",
              "Computed": true
            },
            "first_name": {
              "Type": "String",
              "Computed": true
            },
            "force_sec_auth": {
              "Type": "Bool",
              "Computed": true
            },
            "last_name": {
              "Type": "String",
              "Computed": true
            },
            "password": {
              "Type": "String",
              "Computed": true
            }
          }
        }
      }
    },
    "profitbricks_ipblock": {
      "__timeouts__": [
        "create",
        "update",
        "delete",
        "default"
      ],
      "ips": {
        "Type": "List",
        "Computed": true,
        "Elem": {
          "Type": "SchemaElements",
          "ElementsType": "String"
        }
      },
      "location": {
        "Type": "String",
        "Required": true
      },
      "name": {
        "Type": "String",
        "Optional": true
      },
      "size": {
        "Type": "Int",
        "Required": true
      }
    },
    "profitbricks_ipfailover": {
      "__timeouts__": [
        "create",
        "update",
        "delete",
        "default"
      ],
      "datacenter_id": {
        "Type": "String",
        "Required": true
      },
      "ip": {
        "Type": "String",
        "Required": true
      },
      "lan_id": {
        "Type": "String",
        "Required": true
      },
      "nicuuid": {
        "Type": "String",
        "Required": true
      }
    },
    "profitbricks_lan": {
      "__timeouts__": [
        "create",
        "update",
        "delete",
        "default"
      ],
      "datacenter_id": {
        "Type": "String",
        "Required": true
      },
      "name": {
        "Type": "String",
        "Optional": true
      },
      "public": {
        "Type": "Bool",
        "Required": true
      }
    },
    "profitbricks_loadbalancer": {
      "__timeouts__": [
        "create",
        "update",
        "delete",
        "default"
      ],
      "datacenter_id": {
        "Type": "String",
        "Required": true
      },
      "dhcp": {
        "Type": "Bool",
        "Optional": true
      },
      "ip": {
        "Type": "String",
        "Optional": true
      },
      "name": {
        "Type": "String",
        "Required": true
      },
      "nic_ids": {
        "Type": "List",
        "Required": true,
        "Elem": {
          "Type": "SchemaElements",
          "ElementsType": "String"
        }
      }
    },
    "profitbricks_nic": {
      "__timeouts__": [
        "create",
        "update",
        "delete",
        "default"
      ],
      "datacenter_id": {
        "Type": "String",
        "Required": true
      },
      "dhcp": {
        "Type": "Bool",
        "Optional": true
      },
      "firewall_active": {
        "Type": "Bool",
        "Optional": true
      },
      "ip": {
        "Type": "String",
        "Optional": true
      },
      "ips": {
        "Type": "List",
        "Computed": true,
        "Elem": {
          "Type": "SchemaElements",
          "ElementsType": "String"
        }
      },
      "lan": {
        "Type": "Int",
        "Required": true
      },
      "name": {
        "Type": "String",
        "Optional": true
      },
      "nat": {
        "Type": "Bool",
        "Optional": true
      },
      "server_id": {
        "Type": "String",
        "Required": true
      }
    },
    "profitbricks_server": {
      "__timeouts__": [
        "create",
        "update",
        "delete",
        "default"
      ],
      "availability_zone": {
        "Type": "String",
        "Optional": true
      },
      "boot_cdrom": {
        "Type": "String",
        "Computed": true
      },
      "boot_image": {
        "Type": "String",
        "Computed": true
      },
      "boot_volume": {
        "Type": "String",
        "Computed": true
      },
      "cores": {
        "Type": "Int",
        "Required": true
      },
      "cpu_family": {
        "Type": "String",
        "Optional": true,
        "Computed": true
      },
      "datacenter_id": {
        "Type": "String",
        "Required": true
      },
      "firewallrule_id": {
        "Type": "String",
        "Computed": true
      },
      "image_name": {
        "Type": "String",
        "Optional": true,
        "Computed": true,
        "ConflictsWith": [
          "volume.0.image_name"
        ]
      },
      "image_password": {
        "Type": "String",
        "Optional": true,
        "Computed": true,
        "ConflictsWith": [
          "volume.0.image_password"
        ]
      },
      "licence_type": {
        "Type": "String",
        "Optional": true
      },
      "name": {
        "Type": "String",
        "Required": true
      },
      "nic": {
        "Type": "List",
        "Required": true,
        "MaxItems": 1,
        "Elem": {
          "Type": "SchemaInfo",
          "Info": {
            "dhcp": {
              "Type": "Bool",
              "Optional": true
            },
            "firewall": {
              "Type": "List",
              "Optional": true,
              "MaxItems": 1,
              "Elem": {
                "Type": "SchemaInfo",
                "Info": {
                  "icmp_code": {
                    "Type": "String",
                    "Optional": true
                  },
                  "icmp_type": {
                    "Type": "String",
                    "Optional": true
                  },
                  "ip": {
                    "Type": "String",
                    "Optional": true,
                    "Computed": true
                  },
                  "ips": {
                    "Type": "List",
                    "Optional": true,
                    "Elem": {
                      "Type": "SchemaElements",
                      "ElementsType": "String"
                    }
                  },
                  "name": {
                    "Type": "String",
                    "Optional": true
                  },
                  "port_range_end": {
                    "Type": "Int",
                    "Optional": true
                  },
                  "port_range_start": {
                    "Type": "Int",
                    "Optional": true
                  },
                  "protocol": {
                    "Type": "String",
                    "Required": true
                  },
                  "source_ip": {
                    "Type": "String",
                    "Optional": true
                  },
                  "source_mac": {
                    "Type": "String",
                    "Optional": true
                  },
                  "target_ip": {
                    "Type": "String",
                    "Optional": true
                  }
                }
              }
            },
            "firewall_active": {
              "Type": "Bool",
              "Optional": true
            },
            "ip": {
              "Type": "String",
              "Optional": true
            },
            "ips": {
              "Type": "List",
              "Computed": true,
              "Elem": {
                "Type": "SchemaElements",
                "ElementsType": "String"
              }
            },
            "lan": {
              "Type": "Int",
              "Required": true
            },
            "name": {
              "Type": "String",
              "Optional": true
            },
            "nat": {
              "Type": "Bool",
              "Optional": true
            }
          }
        }
      },
      "primary_ip": {
        "Type": "String",
        "Computed": true
      },
      "primary_nic": {
        "Type": "String",
        "Computed": true
      },
      "ram": {
        "Type": "Int",
        "Required": true
      },
      "ssh_key_path": {
        "Type": "List",
        "Optional": true,
        "Computed": true,
        "ConflictsWith": [
          "volume.0.ssh_key_path"
        ],
        "Elem": {
          "Type": "SchemaElements",
          "ElementsType": "String"
        }
      },
      "volume": {
        "Type": "List",
        "Required": true,
        "MaxItems": 1,
        "Elem": {
          "Type": "SchemaInfo",
          "Info": {
            "availability_zone": {
              "Type": "String",
              "Optional": true,
              "Computed": true
            },
            "bus": {
              "Type": "String",
              "Optional": true,
              "Computed": true
            },
            "disk_type": {
              "Type": "String",
              "Required": true
            },
            "image_aliases": {
              "Type": "List",
              "Computed": true,
              "Elem": {
                "Type": "SchemaElements",
                "ElementsType": "String"
              }
            },
            "image_name": {
              "Type": "String",
              "Optional": true,
              "ConflictsWith": [
                "image_name"
              ],
              "Deprecated": "Please use image_name under server level"
            },
            "image_password": {
              "Type": "String",
              "Optional": true,
              "ConflictsWith": [
                "image_password"
              ],
              "Deprecated": "Please use image_password under server level"
            },
            "licence_type": {
              "Type": "String",
              "Optional": true,
              "Computed": true
            },
            "name": {
              "Type": "String",
              "Optional": true
            },
            "size": {
              "Type": "Int",
              "Required": true
            },
            "ssh_key_path": {
              "Type": "List",
              "Optional": true,
              "Deprecated": "Please use ssh_key_path under server level",
              "Elem": {
                "Type": "SchemaElements",
                "ElementsType": "String"
              }
            }
          }
        }
      }
    },
    "profitbricks_share": {
      "__timeouts__": [
        "create",
        "update",
        "delete",
        "default"
      ],
      "edit_privilege": {
        "Type": "Bool",
        "Required": true
      },
      "group_id": {
        "Type": "String",
        "Required": true
      },
      "resource_id": {
        "Type": "String",
        "Required": true
      },
      "share_privilege": {
        "Type": "Bool",
        "Required": true
      }
    },
    "profitbricks_snapshot": {
      "__timeouts__": [
        "create",
        "update",
        "delete",
        "default"
      ],
      "datacenter_id": {
        "Type": "String",
        "Required": true
      },
      "name": {
        "Type": "String",
        "Required": true
      },
      "volume_id": {
        "Type": "String",
        "Required": true
      }
    },
    "profitbricks_user": {
      "__timeouts__": [
        "create",
        "update",
        "delete",
        "default"
      ],
      "administrator": {
        "Type": "Bool",
        "Required": true
      },
      "email": {
        "Type": "String",
        "Required": true
      },
      "first_name": {
        "Type": "String",
        "Required": true
      },
      "force_sec_auth": {
        "Type": "Bool",
        "Required": true
      },
      "last_name": {
        "Type": "String",
        "Required": true
      },
      "password": {
        "Type": "String",
        "Required": true
      }
    },
    "profitbricks_volume": {
      "__timeouts__": [
        "create",
        "update",
        "delete",
        "default"
      ],
      "availability_zone": {
        "Type": "String",
        "Optional": true
      },
      "bus": {
        "Type": "String",
        "Optional": true
      },
      "datacenter_id": {
        "Type": "String",
        "Required": true
      },
      "disk_type": {
        "Type": "String",
        "Required": true
      },
      "image_name": {
        "Type": "String",
        "Optional": true
      },
      "image_password": {
        "Type": "String",
        "Optional": true
      },
      "licence_type": {
        "Type": "String",
        "Optional": true
      },
      "name": {
        "Type": "String",
        "Optional": true
      },
      "server_id": {
        "Type": "String",
        "Required": true
      },
      "size": {
        "Type": "Int",
        "Required": true
      },
      "ssh_key_path": {
        "Type": "List",
        "Optional": true,
        "Elem": {
          "Type": "SchemaElements",
          "ElementsType": "String"
        }
      },
      "sshkey": {
        "Type": "String",
        "Computed": true
      }
    }
  },
  "data-sources": {
    "profitbricks_datacenter": {
      "id": {
        "Type": "String",
        "Optional": true
      },
      "location": {
        "Type": "String",
        "Optional": true
      },
      "name": {
        "Type": "String",
        "Optional": true
      }
    },
    "profitbricks_image": {
      "location": {
        "Type": "String",
        "Optional": true
      },
      "name": {
        "Type": "String",
        "Optional": true
      },
      "type": {
        "Type": "String",
        "Optional": true
      },
      "version": {
        "Type": "String",
        "Optional": true
      }
    },
    "profitbricks_location": {
      "feature": {
        "Type": "String",
        "Optional": true
      },
      "name": {
        "Type": "String",
        "Optional": true
      }
    },
    "profitbricks_resource": {
      "resource_id": {
        "Type": "String",
        "Optional": true
      },
      "resource_type": {
        "Type": "String",
        "Optional": true
      }
    },
    "profitbricks_snapshot": {
      "location": {
        "Type": "String",
        "Optional": true
      },
      "name": {
        "Type": "String",
        "Required": true
      },
      "size": {
        "Type": "Int",
        "Optional": true
      }
    }
  }
}